Workbook

Sheet README
A1: 項目 | B1: 内容
A2: このファイルの目的 | B2: 個人投資の『元帳（Transactions）→評価（Holdings）→配当（Dividends）→分析（Analytics）』を一元管理するためのテンプレートです。
A3: 使い方（最短） | B3: 1) Transactionsに取引を追加（買/売/配当/手数料）。 2) Pricesに『現在値』と『為替レート』を入力。 3) Holdingsで評価額・損益を確認。 4) Dividendsで配当の年次合計を確認。 ※ 現在値・為替は自動取得しません（手入力 or 後でAPI連携拡張）。
A4: 重要ルール | B4: ・Transactionsが唯一の“元データ”。他シートは参照のみ。 ・為替（FX to EUR）は約定日のレートを確定値として記録してください（後から変えない）。 ・Average Costは簡易法（買い注文の加重平均）。厳密な税ロット（FIFO/LIFO）はTransactionsで管理してください。
A5: 拡張のヒント（後でPython化） | B5: ・VaR/ESや効率的フロンティアはPython（pandas/numpy）に渡すと高速・高精度。 ・APIで価格・為替を自動更新し、AnalyticsのXIRRまで自動化可能。
A6: 注意 | B6: Excel関数は英語名（SUMIFS/XLOOKUPなど）で記述。Excelの表示言語がドイツ語/日本語でも内部的に動作します。

Sheet Transactions
A1: Date | B1: Action | C1: Type | D1: Ticker | E1: ISIN | F1: Exchange | G1: Qty | H1: Price (Local) | I1: Currency | J1: FX to EUR | K1: Price (EUR) | L1: Fees (EUR) | M1: Total (EUR) | N1: CashFlow (EUR)
A2: 45957 | B2: Buy | C2: Stocks | D2: BMW | E2: DE0005190003 | F2: Trading Republic | G2: 1.005148 | H2: 81.57 | I2: EUR | J2: 1 | K2: =H2*J2 | L2: 1 | M2: =G2*K2+L2 | N2: =IF(B2="Buy",-(G2*K2+L2),(G2*K2-L2))
A3: 45957 | B3: Buy | C3: Stocks | D3: Coca-Cola | E3: US1912161007 | F3: Trading Republic | G3: 1.004352 | H3: 59.74 | I3: EUR | J3: 1 | K3: =H3*J3 | L3: 1 | M3: =G3*K3+L3 | N3: =IF(B3="Buy",-(G3*K3+L3),(G3*K3-L3))
A4: 45957 | B4: Buy | C4: Stocks | D4: Super Micro Computing | E4: US86800U3023 | F4: Trading Republic | G4: 1.004795 | H4: 43.78 | I4: EUR | J4: 1 | K4: =H4*J4 | L4: 1 | M4: =G4*K4+L4 | N4: =IF(B4="Buy",-(G4*K4+L4),(G4*K4-L4))
A5: 45957 | B5: Buy | C5: Stocks | D5: Mitsubishi UFJ | E5: JP3902900004 | F5: Trading Republic | G5: 10.029316 | H5: 12.96 | I5: EUR | J5: 1 | K5: =H5*J5 | L5: 1 | M5: =G5*K5+L5 | N5: =IF(B5="Buy",-(G5*K5+L5),(G5*K5-L5))
A6: 45957 | B6: Buy | C6: ETF | D6: Core MSCI World USD (Acc) | E6: IE00B4L5Y983 | F6: Trading Republic | G6: 1.006198 | H6: 111.31 | I6: EUR | J6: 1 | K6: =H6*J6 | L6: 1 | M6: =G6*K6+L6 | N6: =IF(B6="Buy",-(G6*K6+L6),(G6*K6-L6))
A7: 45960 | B7: Buy | C7: ETF | D7: Global Infrastructure USD (Acc) | E7: IE000CK5G8J7 | F7: Trading Republic | G7: 13.835085 | H7: 5.42 | I7: EUR | J7: 1 | K7: =H7*J7 | L7: 1 | M7: =G7*K7+L7 | N7: =IF(B7="Buy",-(G7*K7+L7),(G7*K7-L7))
A8: 45960 | B8: Buy | C8: ETF | D8: Core MSCI EM IMI USD (Acc) | E8: IE00BKM4GZ66 | F8: Trading Republic | G8: 3.856338 | H8: 38.9 | I8: EUR | J8: 1 | K8: =H8*J8 | L8: 1 | M8: =G8*K8+L8 | N8: =IF(B8="Buy",-(G8*K8+L8),(G8*K8-L8))
A9: 45960 | B9: Buy | C9: ETF | D9: Eurozone Government Bond EUR (Acc) | E9: IE00BH04GL39 | F9: Trading Republic | G9: 3.111 | H9: 24.11 | I9: EUR | J9: 1 | K9: =H9*J9 | L9: 1 | M9: =G9*K9+L9 | N9: =IF(B9="Buy",-(G9*K9+L9),(G9*K9-L9))
A10: 45960 | B10: Buy | C10: ETF | D10: MSCI Japan USD (Acc) | E10: LU0274209740 | F10: Trading Republic | G10: 2.604347 | H10: 86.39 | I10: EUR | J10: 1 | K10: =H10*J10 | L10: 1 | M10: =G10*K10+L10 | N10: =IF(B10="Buy",-(G10*K10+L10),(G10*K10-L10))
A11: 45960 | B11: Buy | C11: ETF | D11: Core MSCI World USD (Acc) | E11: IE00B4L5Y983 | F11: Trading Republic | G11: 8.016821 | H11: 111.75 | I11: EUR | J11: 1 | K11: =H11*J11 | L11: 1 | M11: =G11*K11+L11 | N11: =IF(B11="Buy",-(G11*K11+L11),(G11*K11-L11))
A12: 45960 | B12: Buy | C12: ETF | D12: Physical Gold USD (Acc) | E12: IE00B4ND3602 | F12: Trading Republic | G12: 1.114661 | H12: 67.29 | I12: EUR | J12: 1 | K12: =H12*J12 | L12: 1 | M12: =G12*K12+L12 | N12: =IF(B12="Buy",-(G12*K12+L12),(G12*K12-L12))
A13: 45966 | B13: Sell | C13: Stocks | D13: BMW | E13: DE0005190003 | F13: Trading Republic | G13: 1.005148 | H13: 85.72 | I13: EUR | J13: 1 | K13: =H13*J13 | L13: 1 | M13: =G13*K13+L13 | N13: =IF(B13="Buy",-(G13*K13+L13),(G13*K13-L13))

Sheet Map
A1: ISIN | B1: Ticker | C1: Exchange | D1: Currency | E1: Name
A2: DE0005190003 | B2: BMW.DE | C2: XETR | D2: EUR
A3: US1912161007 | B3: KO | C3: NYSE | D3: USD
A4: US86800U3023 | B4: SMCI | C4: NASDAQ | D4: USD
A5: JP3902900004 | B5: 8306.T | C5: TSE | D5: JPY
A6: IE00B4L5Y983 | B6: EUNL.DE | C6: XETR | D6: EUR
A7: IE000CK5G8J7 | B7: CBUX.DE | C7: XETR | D7: EUR
A8: IE00BKM4GZ66 | B8: IS3N.DE | C8: XETR | D8: EUR
A9: IE00BH04GL39 | B9: VGEA.DE | C9: XETR | D9: EUR
A10: LU0274209740 | B10: DBXJ.DE | C10: XETR | D10: EUR
A11: IE00B4ND3602 | B11: PPFB.DE | C11: XETR | D11: EUR

Sheet Prices
A1: ISIN | B1: Ticker | C1: Currency | D1: Last Timestamp (Local) | E1: Last Timestamp (UTC) | F1: Last Close (Local) | G1: FX to EUR | H1: Last Close (EUR) | I1: Source
A2: DE0005190003 | B2: BMW.DE | C2: EUR | D2: 2025-11-06T13:13:00+01:00 | E2: 2025-11-06T12:13:00+00:00 | F2: 84.18 | G2: 1 | H2: 84.18 | I2: 1m
A3: US1912161007 | B3: KO | C3: USD | D3: 2025-11-05T15:59:00-05:00 | E3: 2025-11-05T20:59:00+00:00 | F3: 68.495003 | G3: 0.86780002 | H3: 59.439965 | I3: 1m
A4: US86800U3023 | B4: SMCI | C4: USD | D4: 2025-11-05T15:59:00-05:00 | E4: 2025-11-05T20:59:00+00:00 | F4: 42.029999 | G4: 0.86780002 | H4: 36.473634 | I4: 1m
A5: JP3902900004 | B5: 8306.T | C5: JPY | D5: 2025-11-06T15:24:00+09:00 | E5: 2025-11-06T06:24:00+00:00 | F5: 2326.5 | G5: 0.0056474838 | H5: 13.138871 | I5: 1m
A6: IE00B4L5Y983 | B6: EUNL.DE | C6: EUR | D6: 2025-11-06T13:14:00+01:00 | E6: 2025-11-06T12:14:00+00:00 | F6: 111.51 | G6: 1 | H6: 111.51 | I6: 1m
A7: IE000CK5G8J7 | B7: CBUX.DE | C7: EUR | D7: 2025-11-06T13:12:00+01:00 | E7: 2025-11-06T12:12:00+00:00 | F7: 5.4439998 | G7: 1 | H7: 5.4439998 | I7: 1m
A8: IE00BKM4GZ66 | B8: IS3N.DE | C8: EUR | D8: 2025-11-06T13:14:00+01:00 | E8: 2025-11-06T12:14:00+00:00 | F8: 38.851002 | G8: 1 | H8: 38.851002 | I8: 1m
A9: IE00BH04GL39 | B9: VGEA.DE | C9: EUR | D9: 2025-11-06T13:12:00+01:00 | E9: 2025-11-06T12:12:00+00:00 | F9: 24.077 | G9: 1 | H9: 24.077 | I9: 1m
A10: LU0274209740 | B10: DBXJ.DE | C10: EUR | D10: 2025-11-06T13:12:00+01:00 | E10: 2025-11-06T12:12:00+00:00 | F10: 87.001999 | G10: 1 | H10: 87.001999 | I10: 1m
A11: IE00B4ND3602 | B11: PPFB.DE | C11: EUR | D11: 2025-11-06T13:13:00+01:00 | E11: 2025-11-06T12:13:00+00:00 | F11: 67.629997 | G11: 1 | H11: 67.629997 | I11: 1m

Sheet Dividends
A1: Date | B1: Ticker | C1: Dividend per Share (Local) | D1: Qty | E1: Gross Amount (Local) | F1: Withholding Tax (Local) | G1: Fees (Local) | H1: Net Amount (Local) | I1: Currency | J1: FX to EUR | K1: Net Amount (EUR)
K2: =IF(ROW()>1, J2*I2, "")
A3: Year | B3: Total Dividends (EUR)
A4: 2025 | B4: =SUMIFS(Dividends!K:K,Dividends!A:A,">="&DATE(A2,1,1),Dividends!A:A,"<="&DATE(A2,12,31))
A5: 2026 | B5: =SUMIFS(Dividends!K:K,Dividends!A:A,">="&DATE(A3,1,1),Dividends!A:A,"<="&DATE(A3,12,31))
A6: 2027 | B6: =SUMIFS(Dividends!K:K,Dividends!A:A,">="&DATE(A4,1,1),Dividends!A:A,"<="&DATE(A4,12,31))

Sheet Positions
A1: ISIN | B1: Name | C1: Type | D1: Qty | E1: Avg Cost (EUR) | F1: Cost Basis (EUR) | G1: Ticker | H1: Currency | I1: Last Date | J1: Last Close (EUR) | K1: Market Value (EUR) | L1: Unrealized P&L (EUR) | M1: Unrealized P&L (%) | N1: Realized P&L (EUR)
A2: {=_xlfn.LET( _xlpm.E, Transactions!E2:E1000, _xlpm.B, Transactions!B2:B1000, _xlpm.G, Transactions!G2:G1000, _xlfn._xlws.SORT( _xlfn.UNIQUE( _xlfn._xlws.FILTER( _xlpm.E, (_xlpm.E<>"")* (SUMIFS(_xlpm.G,_xlpm.E,_xlpm.E,_xlpm.B,"Buy")-SUMIFS(_xlpm.G,_xlpm.E,_xlpm.E,_xlpm.B,"Sell")>0) ) ) ) )} | B2: =IF(A2="","",_xlfn.XLOOKUP(A2,Transactions!E:E,Transactions!D:D,"")) | C2: =IF(A2="","",_xlfn.XLOOKUP(A2,Transactions!E:E,Transactions!C:C,"")) | D2: =IF(A2="","", SUMIFS(Transactions!G:G, Transactions!E:E, A2, Transactions!B:B, "Buy") - SUMIFS(Transactions!G:G, Transactions!E:E, A2, Transactions!B:B, "Sell") ) | E2: =IF(D2>0, SUMIFS(Transactions!M:M, Transactions!E:E, A2, Transactions!B:B, "Buy") / SUMIFS(Transactions!G:G, Transactions!E:E, A2, Transactions!B:B, "Buy"), "" ) | F2: =IF(D2>0, D2 * E2, "") | G2: =IF(A2="","",_xlfn.XLOOKUP(A2,Map!A:A,Map!B:B,"")) | H2: =IF(A2="","",_xlfn.XLOOKUP(A2,Map!A:A,Map!D:D,"EUR")) | I2: =IF(A2="","",_xlfn.XLOOKUP(A2,Prices!A:A,Prices!D:D,"")) | J2: =IF(A2="","",_xlfn.XLOOKUP(A2,Prices!A:A,Prices!H:H,"")) | K2: =IF(AND(D2>0,J2<>""), D2*J2, "") | L2: =IF(AND(F2<>"",K2<>""), K2-F2, "") | M2: =IF(OR(F2<0,F2="")," ",L2/F2) | N2: =_xlfn.LET( _xlpm.isin,A2, _xlpm.buys_amt, SUMIFS(Transactions!N:N,Transactions!E:E,_xlpm.isin,Transactions!B:B,"Buy"), _xlpm.buys_qty, SUMIFS(Transactions!G:G,Transactions!E:E,_xlpm.isin,Transactions!B:B,"Buy"), _xlpm.sold_qty, SUMIFS(Transactions!G:G,Transactions!E:E,_xlpm.isin,Transactions!B:B,"Sell"), _xlpm.proceeds, SUMIFS(Transactions!N:N,Transactions!E:E,_xlpm.isin,Transactions!B:B,"Sell"), _xlpm.avg_cost, -_xlpm.buys_amt/_xlpm.buys_qty, IFERROR(_xlpm.proceeds - _xlpm.sold_qty*_xlpm.avg_cost,0) )
A3: IE00B4L5Y983 | B3: =IF(A3="","",_xlfn.XLOOKUP(A3,Transactions!E:E,Transactions!D:D,"")) | C3: =IF(A3="","",_xlfn.XLOOKUP(A3,Transactions!E:E,Transactions!C:C,"")) | D3: =IF(A3="","", SUMIFS(Transactions!G:G, Transactions!E:E, A3, Transactions!B:B, "Buy") - SUMIFS(Transactions!G:G, Transactions!E:E, A3, Transactions!B:B, "Sell") ) | E3: =IF(D3>0, SUMIFS(Transactions!M:M, Transactions!E:E, A3, Transactions!B:B, "Buy") / SUMIFS(Transactions!G:G, Transactions!E:E, A3, Transactions!B:B, "Buy"), "" ) | F3: =IF(D3>0, D3 * E3, "") | G3: =IF(A3="","",_xlfn.XLOOKUP(A3,Map!A:A,Map!B:B,"")) | H3: =IF(A3="","",_xlfn.XLOOKUP(A3,Map!A:A,Map!D:D,"EUR")) | I3: =IF(A3="","",_xlfn.XLOOKUP(A3,Prices!A:A,Prices!D:D,"")) | J3: =IF(A3="","",_xlfn.XLOOKUP(A3,Prices!A:A,Prices!H:H,"")) | K3: =IF(AND(D3>0,J3<>""), D3*J3, "") | L3: =IF(AND(F3<>"",K3<>""), K3-F3, "") | M3: =IF(OR(F3<0,F3="")," ",L3/F3) | N3: =_xlfn.LET( _xlpm.isin,A3, _xlpm.buys_amt, SUMIFS(Transactions!N:N,Transactions!E:E,_xlpm.isin,Transactions!B:B,"Buy"), _xlpm.buys_qty, SUMIFS(Transactions!G:G,Transactions!E:E,_xlpm.isin,Transactions!B:B,"Buy"), _xlpm.sold_qty, SUMIFS(Transactions!G:G,Transactions!E:E,_xlpm.isin,Transactions!B:B,"Sell"), _xlpm.proceeds, SUMIFS(Transactions!N:N,Transactions!E:E,_xlpm.isin,Transactions!B:B,"Sell"), _xlpm.avg_cost, -_xlpm.buys_amt/_xlpm.buys_qty, IFERROR(_xlpm.proceeds - _xlpm.sold_qty*_xlpm.avg_cost,0) )
A4: IE00B4ND3602 | B4: =IF(A4="","",_xlfn.XLOOKUP(A4,Transactions!E:E,Transactions!D:D,"")) | C4: =IF(A4="","",_xlfn.XLOOKUP(A4,Transactions!E:E,Transactions!C:C,"")) | D4: =IF(A4="","", SUMIFS(Transactions!G:G, Transactions!E:E, A4, Transactions!B:B, "Buy") - SUMIFS(Transactions!G:G, Transactions!E:E, A4, Transactions!B:B, "Sell") ) | E4: =IF(D4>0, SUMIFS(Transactions!M:M, Transactions!E:E, A4, Transactions!B:B, "Buy") / SUMIFS(Transactions!G:G, Transactions!E:E, A4, Transactions!B:B, "Buy"), "" ) | F4: =IF(D4>0, D4 * E4, "") | G4: =IF(A4="","",_xlfn.XLOOKUP(A4,Map!A:A,Map!B:B,"")) | H4: =IF(A4="","",_xlfn.XLOOKUP(A4,Map!A:A,Map!D:D,"EUR")) | I4: =IF(A4="","",_xlfn.XLOOKUP(A4,Prices!A:A,Prices!D:D,"")) | J4: =IF(A4="","",_xlfn.XLOOKUP(A4,Prices!A:A,Prices!H:H,"")) | K4: =IF(AND(D4>0,J4<>""), D4*J4, "") | L4: =IF(AND(F4<>"",K4<>""), K4-F4, "") | M4: =IF(OR(F4<0,F4="")," ",L4/F4) | N4: =_xlfn.LET( _xlpm.isin,A4, _xlpm.buys_amt, SUMIFS(Transactions!N:N,Transactions!E:E,_xlpm.isin,Transactions!B:B,"Buy"), _xlpm.buys_qty, SUMIFS(Transactions!G:G,Transactions!E:E,_xlpm.isin,Transactions!B:B,"Buy"), _xlpm.sold_qty, SUMIFS(Transactions!G:G,Transactions!E:E,_xlpm.isin,Transactions!B:B,"Sell"), _xlpm.proceeds, SUMIFS(Transactions!N:N,Transactions!E:E,_xlpm.isin,Transactions!B:B,"Sell"), _xlpm.avg_cost, -_xlpm.buys_amt/_xlpm.buys_qty, IFERROR(_xlpm.proceeds - _xlpm.sold_qty*_xlpm.avg_cost,0) )
A5: IE00BH04GL39 | B5: =IF(A5="","",_xlfn.XLOOKUP(A5,Transactions!E:E,Transactions!D:D,"")) | C5: =IF(A5="","",_xlfn.XLOOKUP(A5,Transactions!E:E,Transactions!C:C,"")) | D5: =IF(A5="","", SUMIFS(Transactions!G:G, Transactions!E:E, A5, Transactions!B:B, "Buy") - SUMIFS(Transactions!G:G, Transactions!E:E, A5, Transactions!B:B, "Sell") ) | E5: =IF(D5>0, SUMIFS(Transactions!M:M, Transactions!E:E, A5, Transactions!B:B, "Buy") / SUMIFS(Transactions!G:G, Transactions!E:E, A5, Transactions!B:B, "Buy"), "" ) | F5: =IF(D5>0, D5 * E5, "") | G5: =IF(A5="","",_xlfn.XLOOKUP(A5,Map!A:A,Map!B:B,"")) | H5: =IF(A5="","",_xlfn.XLOOKUP(A5,Map!A:A,Map!D:D,"EUR")) | I5: =IF(A5="","",_xlfn.XLOOKUP(A5,Prices!A:A,Prices!D:D,"")) | J5: =IF(A5="","",_xlfn.XLOOKUP(A5,Prices!A:A,Prices!H:H,"")) | K5: =IF(AND(D5>0,J5<>""), D5*J5, "") | L5: =IF(AND(F5<>"",K5<>""), K5-F5, "") | M5: =IF(OR(F5<0,F5="")," ",L5/F5) | N5: =_xlfn.LET( _xlpm.isin,A5, _xlpm.buys_amt, SUMIFS(Transactions!N:N,Transactions!E:E,_xlpm.isin,Transactions!B:B,"Buy"), _xlpm.buys_qty, SUMIFS(Transactions!G:G,Transactions!E:E,_xlpm.isin,Transactions!B:B,"Buy"), _xlpm.sold_qty, SUMIFS(Transactions!G:G,Transactions!E:E,_xlpm.isin,Transactions!B:B,"Sell"), _xlpm.proceeds, SUMIFS(Transactions!N:N,Transactions!E:E,_xlpm.isin,Transactions!B:B,"Sell"), _xlpm.avg_cost, -_xlpm.buys_amt/_xlpm.buys_qty, IFERROR(_xlpm.proceeds - _xlpm.sold_qty*_xlpm.avg_cost,0) )
A6: IE00BKM4GZ66 | B6: =IF(A6="","",_xlfn.XLOOKUP(A6,Transactions!E:E,Transactions!D:D,"")) | C6: =IF(A6="","",_xlfn.XLOOKUP(A6,Transactions!E:E,Transactions!C:C,"")) | D6: =IF(A6="","", SUMIFS(Transactions!G:G, Transactions!E:E, A6, Transactions!B:B, "Buy") - SUMIFS(Transactions!G:G, Transactions!E:E, A6, Transactions!B:B, "Sell") ) | E6: =IF(D6>0, SUMIFS(Transactions!M:M, Transactions!E:E, A6, Transactions!B:B, "Buy") / SUMIFS(Transactions!G:G, Transactions!E:E, A6, Transactions!B:B, "Buy"), "" ) | F6: =IF(D6>0, D6 * E6, "") | G6: =IF(A6="","",_xlfn.XLOOKUP(A6,Map!A:A,Map!B:B,"")) | H6: =IF(A6="","",_xlfn.XLOOKUP(A6,Map!A:A,Map!D:D,"EUR")) | I6: =IF(A6="","",_xlfn.XLOOKUP(A6,Prices!A:A,Prices!D:D,"")) | J6: =IF(A6="","",_xlfn.XLOOKUP(A6,Prices!A:A,Prices!H:H,"")) | K6: =IF(AND(D6>0,J6<>""), D6*J6, "") | L6: =IF(AND(F6<>"",K6<>""), K6-F6, "") | M6: =IF(OR(F6<0,F6="")," ",L6/F6) | N6: =_xlfn.LET( _xlpm.isin,A6, _xlpm.buys_amt, SUMIFS(Transactions!N:N,Transactions!E:E,_xlpm.isin,Transactions!B:B,"Buy"), _xlpm.buys_qty, SUMIFS(Transactions!G:G,Transactions!E:E,_xlpm.isin,Transactions!B:B,"Buy"), _xlpm.sold_qty, SUMIFS(Transactions!G:G,Transactions!E:E,_xlpm.isin,Transactions!B:B,"Sell"), _xlpm.proceeds, SUMIFS(Transactions!N:N,Transactions!E:E,_xlpm.isin,Transactions!B:B,"Sell"), _xlpm.avg_cost, -_xlpm.buys_amt/_xlpm.buys_qty, IFERROR(_xlpm.proceeds - _xlpm.sold_qty*_xlpm.avg_cost,0) )
A7: JP3902900004 | B7: =IF(A7="","",_xlfn.XLOOKUP(A7,Transactions!E:E,Transactions!D:D,"")) | C7: =IF(A7="","",_xlfn.XLOOKUP(A7,Transactions!E:E,Transactions!C:C,"")) | D7: =IF(A7="","", SUMIFS(Transactions!G:G, Transactions!E:E, A7, Transactions!B:B, "Buy") - SUMIFS(Transactions!G:G, Transactions!E:E, A7, Transactions!B:B, "Sell") ) | E7: =IF(D7>0, SUMIFS(Transactions!M:M, Transactions!E:E, A7, Transactions!B:B, "Buy") / SUMIFS(Transactions!G:G, Transactions!E:E, A7, Transactions!B:B, "Buy"), "" ) | F7: =IF(D7>0, D7 * E7, "") | G7: =IF(A7="","",_xlfn.XLOOKUP(A7,Map!A:A,Map!B:B,"")) | H7: =IF(A7="","",_xlfn.XLOOKUP(A7,Map!A:A,Map!D:D,"EUR")) | I7: =IF(A7="","",_xlfn.XLOOKUP(A7,Prices!A:A,Prices!D:D,"")) | J7: =IF(A7="","",_xlfn.XLOOKUP(A7,Prices!A:A,Prices!H:H,"")) | K7: =IF(AND(D7>0,J7<>""), D7*J7, "") | L7: =IF(AND(F7<>"",K7<>""), K7-F7, "") | M7: =IF(OR(F7<0,F7="")," ",L7/F7) | N7: =_xlfn.LET( _xlpm.isin,A7, _xlpm.buys_amt, SUMIFS(Transactions!N:N,Transactions!E:E,_xlpm.isin,Transactions!B:B,"Buy"), _xlpm.buys_qty, SUMIFS(Transactions!G:G,Transactions!E:E,_xlpm.isin,Transactions!B:B,"Buy"), _xlpm.sold_qty, SUMIFS(Transactions!G:G,Transactions!E:E,_xlpm.isin,Transactions!B:B,"Sell"), _xlpm.proceeds, SUMIFS(Transactions!N:N,Transactions!E:E,_xlpm.isin,Transactions!B:B,"Sell"), _xlpm.avg_cost, -_xlpm.buys_amt/_xlpm.buys_qty, IFERROR(_xlpm.proceeds - _xlpm.sold_qty*_xlpm.avg_cost,0) )
A8: LU0274209740 | B8: =IF(A8="","",_xlfn.XLOOKUP(A8,Transactions!E:E,Transactions!D:D,"")) | C8: =IF(A8="","",_xlfn.XLOOKUP(A8,Transactions!E:E,Transactions!C:C,"")) | D8: =IF(A8="","", SUMIFS(Transactions!G:G, Transactions!E:E, A8, Transactions!B:B, "Buy") - SUMIFS(Transactions!G:G, Transactions!E:E, A8, Transactions!B:B, "Sell") ) | E8: =IF(D8>0, SUMIFS(Transactions!M:M, Transactions!E:E, A8, Transactions!B:B, "Buy") / SUMIFS(Transactions!G:G, Transactions!E:E, A8, Transactions!B:B, "Buy"), "" ) | F8: =IF(D8>0, D8 * E8, "") | G8: =IF(A8="","",_xlfn.XLOOKUP(A8,Map!A:A,Map!B:B,"")) | H8: =IF(A8="","",_xlfn.XLOOKUP(A8,Map!A:A,Map!D:D,"EUR")) | I8: =IF(A8="","",_xlfn.XLOOKUP(A8,Prices!A:A,Prices!D:D,"")) | J8: =IF(A8="","",_xlfn.XLOOKUP(A8,Prices!A:A,Prices!H:H,"")) | K8: =IF(AND(D8>0,J8<>""), D8*J8, "") | L8: =IF(AND(F8<>"",K8<>""), K8-F8, "") | M8: =IF(OR(F8<0,F8="")," ",L8/F8) | N8: =_xlfn.LET( _xlpm.isin,A8, _xlpm.buys_amt, SUMIFS(Transactions!N:N,Transactions!E:E,_xlpm.isin,Transactions!B:B,"Buy"), _xlpm.buys_qty, SUMIFS(Transactions!G:G,Transactions!E:E,_xlpm.isin,Transactions!B:B,"Buy"), _xlpm.sold_qty, SUMIFS(Transactions!G:G,Transactions!E:E,_xlpm.isin,Transactions!B:B,"Sell"), _xlpm.proceeds, SUMIFS(Transactions!N:N,Transactions!E:E,_xlpm.isin,Transactions!B:B,"Sell"), _xlpm.avg_cost, -_xlpm.buys_amt/_xlpm.buys_qty, IFERROR(_xlpm.proceeds - _xlpm.sold_qty*_xlpm.avg_cost,0) )
A9: US1912161007 | B9: =IF(A9="","",_xlfn.XLOOKUP(A9,Transactions!E:E,Transactions!D:D,"")) | C9: =IF(A9="","",_xlfn.XLOOKUP(A9,Transactions!E:E,Transactions!C:C,"")) | D9: =IF(A9="","", SUMIFS(Transactions!G:G, Transactions!E:E, A9, Transactions!B:B, "Buy") - SUMIFS(Transactions!G:G, Transactions!E:E, A9, Transactions!B:B, "Sell") ) | E9: =IF(D9>0, SUMIFS(Transactions!M:M, Transactions!E:E, A9, Transactions!B:B, "Buy") / SUMIFS(Transactions!G:G, Transactions!E:E, A9, Transactions!B:B, "Buy"), "" ) | F9: =IF(D9>0, D9 * E9, "") | G9: =IF(A9="","",_xlfn.XLOOKUP(A9,Map!A:A,Map!B:B,"")) | H9: =IF(A9="","",_xlfn.XLOOKUP(A9,Map!A:A,Map!D:D,"EUR")) | I9: =IF(A9="","",_xlfn.XLOOKUP(A9,Prices!A:A,Prices!D:D,"")) | J9: =IF(A9="","",_xlfn.XLOOKUP(A9,Prices!A:A,Prices!H:H,"")) | K9: =IF(AND(D9>0,J9<>""), D9*J9, "") | L9: =IF(AND(F9<>"",K9<>""), K9-F9, "") | M9: =IF(OR(F9<0,F9="")," ",L9/F9) | N9: =_xlfn.LET( _xlpm.isin,A9, _xlpm.buys_amt, SUMIFS(Transactions!N:N,Transactions!E:E,_xlpm.isin,Transactions!B:B,"Buy"), _xlpm.buys_qty, SUMIFS(Transactions!G:G,Transactions!E:E,_xlpm.isin,Transactions!B:B,"Buy"), _xlpm.sold_qty, SUMIFS(Transactions!G:G,Transactions!E:E,_xlpm.isin,Transactions!B:B,"Sell"), _xlpm.proceeds, SUMIFS(Transactions!N:N,Transactions!E:E,_xlpm.isin,Transactions!B:B,"Sell"), _xlpm.avg_cost, -_xlpm.buys_amt/_xlpm.buys_qty, IFERROR(_xlpm.proceeds - _xlpm.sold_qty*_xlpm.avg_cost,0) )
A10: US86800U3023 | B10: =IF(A10="","",_xlfn.XLOOKUP(A10,Transactions!E:E,Transactions!D:D,"")) | C10: =IF(A10="","",_xlfn.XLOOKUP(A10,Transactions!E:E,Transactions!C:C,"")) | D10: =IF(A10="","", SUMIFS(Transactions!G:G, Transactions!E:E, A10, Transactions!B:B, "Buy") - SUMIFS(Transactions!G:G, Transactions!E:E, A10, Transactions!B:B, "Sell") ) | E10: =IF(D10>0, SUMIFS(Transactions!M:M, Transactions!E:E, A10, Transactions!B:B, "Buy") / SUMIFS(Transactions!G:G, Transactions!E:E, A10, Transactions!B:B, "Buy"), "" ) | F10: =IF(D10>0, D10 * E10, "") | G10: =IF(A10="","",_xlfn.XLOOKUP(A10,Map!A:A,Map!B:B,"")) | H10: =IF(A10="","",_xlfn.XLOOKUP(A10,Map!A:A,Map!D:D,"EUR")) | I10: =IF(A10="","",_xlfn.XLOOKUP(A10,Prices!A:A,Prices!D:D,"")) | J10: =IF(A10="","",_xlfn.XLOOKUP(A10,Prices!A:A,Prices!H:H,"")) | K10: =IF(AND(D10>0,J10<>""), D10*J10, "") | L10: =IF(AND(F10<>"",K10<>""), K10-F10, "") | M10: =IF(OR(F10<0,F10="")," ",L10/F10) | N10: =_xlfn.LET( _xlpm.isin,A10, _xlpm.buys_amt, SUMIFS(Transactions!N:N,Transactions!E:E,_xlpm.isin,Transactions!B:B,"Buy"), _xlpm.buys_qty, SUMIFS(Transactions!G:G,Transactions!E:E,_xlpm.isin,Transactions!B:B,"Buy"), _xlpm.sold_qty, SUMIFS(Transactions!G:G,Transactions!E:E,_xlpm.isin,Transactions!B:B,"Sell"), _xlpm.proceeds, SUMIFS(Transactions!N:N,Transactions!E:E,_xlpm.isin,Transactions!B:B,"Sell"), _xlpm.avg_cost, -_xlpm.buys_amt/_xlpm.buys_qty, IFERROR(_xlpm.proceeds - _xlpm.sold_qty*_xlpm.avg_cost,0) )

Sheet Analytics
A1: Metric | B1: Value
A2: As of Date | B2: 2025-11-05
A3: Portfolio Market Value (EUR) | B3: {=SUM(_xlfn._xlws.FILTER(Positions!K:K, Positions!D:D>0))}
A4: Invested (EUR) | B4: =SUMPRODUCT(Positions!D2:D100, Positions!E2:E100)
A5: Realized P/L (EUR) | B5: {=_xlfn.LET( _xlpm.list, _xlfn._xlws.SORT(_xlfn.UNIQUE(_xlfn._xlws.FILTER(Transactions!E:E,(Transactions!E:E<>"")*(ROW(Transactions!E:E)>1)))), SUM( _xlfn.MAP(_xlpm.list, _xlfn.LAMBDA(_xlpm.isin, _xlfn.LET( _xlpm.b_amt, SUMIFS(Transactions!N:N,Transactions!E:E,_xlpm.isin,Transactions!B:B,"Buy"), _xlpm.b_qty, SUMIFS(Transactions!G:G,Transactions!E:E,_xlpm.isin,Transactions!B:B,"Buy"), _xlpm.s_qty, SUMIFS(Transactions!G:G,Transactions!E:E,_xlpm.isin,Transactions!B:B,"Sell"), _xlpm.proc, SUMIFS(Transactions!N:N,Transactions!E:E,_xlpm.isin,Transactions!B:B,"Sell"), IFERROR(_xlpm.proc - _xlpm.s_qty * (-_xlpm.b_amt/_xlpm.b_qty), 0) ) ))) )}
A6: Unrealized P/L (EUR) | B6: =B3-B4
A7: ETF Weight | B7: {=SUM(_xlfn._xlws.FILTER(Positions!K:K,(Positions!C:C="ETF")*(Positions!D:D>0)))/B3}
